omicsguard/__init__.py
omicsguard/cli.py
omicsguard/loader.py
omicsguard/plugin.py
omicsguard/reporter.py
omicsguard/utils.py
omicsguard/validator.py
omicsguard/schemas/default.json
omicsguard-0.1.0.dist-info/METADATA
omicsguard-0.1.0.dist-info/WHEEL
omicsguard-0.1.0.dist-info/entry_points.txt
omicsguard-0.1.0.dist-info/top_level.txt
omicsguard-0.1.0.dist-info/RECORD
