Metadata-Version: 2.4
Name: omicsguard
Version: 0.1.0
Summary: A Serverless-Ready Metadata Validator for GA4GH Genomic Standards
Author-email: Dart <dart@example.com>
Classifier: Programming Language :: Python :: 3
Classifier: License :: OSI Approved :: MIT License
Classifier: Operating System :: OS Independent
Classifier: Topic :: Scientific/Engineering :: Bio-Informatics
Requires-Python: >=3.9
Requires-Dist: jsonschema>=4.0.0
Requires-Dist: click>=8.0.0
Requires-Dist: requests>=2.25.0
Requires-Dist: pyyaml>=6.0
Provides-Extra: dev
Requires-Dist: pytest; extra == "dev"
Requires-Dist: coverage; extra == "dev"
